Metadata-Version: 1.0
Name: hsopdhr
Version: 0.1
Summary: This package generates dhr reports of HSOP in html and pdf formats
Home-page: https://github.com/yarlagadda1990/test
Author: yarlagadda
Author-email: yarlagadda.anusha@gmail.com
License: UNKNOWN
Platform: UNKNOWN
